core/__init__.py
core/response_analysis.py
core/visual_behavior_ophys_dataset.py
dataset/__init__.py
dataset/visual_behavior_ophys_dataset.py
dro/__init__.py
dro/utilities.py
plotting_tools/__init__.py
plotting_tools/basic_plotting.py
roi_mask_analysis/__init__.py
roi_mask_analysis/roi_mask_analysis.py
roi_masks/__init__.py
roi_masks/objectlist.py
sync/__init__.py
sync/dataset.py
sync/process_sync.py
temporal_alignment/__init__.py
temporal_alignment/process_sync.py
temporal_alignment/sync_dataset.py
visual_behavior_ophys/__init__.py
visual_behavior_ophys/dataset/__init__.py
visual_behavior_ophys/dataset/visual_behavior_ophys_dataset.py
visual_behavior_ophys/dro/__init__.py
visual_behavior_ophys/dro/utilities.py
visual_behavior_ophys/plotting_tools/__init__.py
visual_behavior_ophys/plotting_tools/basic_plotting.py
visual_behavior_ophys/response_analysis/__init__.py
visual_behavior_ophys/response_analysis/response_analysis.py
visual_behavior_ophys/roi_mask_analysis/__init__.py
visual_behavior_ophys/roi_mask_analysis/roi_mask_analysis.py
visual_behavior_ophys/temporal_alignment/__init__.py
visual_behavior_ophys/temporal_alignment/process_sync.py
visual_behavior_ophys/temporal_alignment/sync_dataset.py
visual_behavior_ophys-0.1.dist-info/DESCRIPTION.rst
visual_behavior_ophys-0.1.dist-info/METADATA
visual_behavior_ophys-0.1.dist-info/RECORD
visual_behavior_ophys-0.1.dist-info/WHEEL
visual_behavior_ophys-0.1.dist-info/metadata.json
visual_behavior_ophys-0.1.dist-info/top_level.txt
